{
  "date": "2025-09-30",
  "articles": [
    {
      "id": "ace7c50e-42d6-408b-9042-943fdf204389",
      "title": "India's Strategy to Eliminate Naxalism by 2026",
      "category": "NEWS",
      "time_to_read": "6m read",
      "cached_at": "2025-09-30T17:09:11.361Z"
    },
    {
      "id": "02c1387a-79ab-451f-9739-a5aa11745261",
      "title": "Trump's 20-Point Gaza Peace Plan and Hamas Response",
      "category": "NEWS",
      "time_to_read": "6m read",
      "cached_at": "2025-09-30T17:09:11.361Z"
    },
    {
      "id": "98a3081a-1c2f-48c4-97f4-62c68ab7a689",
      "title": "Russia's Major 12-Hour Attack on Ukraine with Drones and Missiles",
      "category": "NEWS",
      "time_to_read": "4m read",
      "cached_at": "2025-09-30T17:09:11.361Z"
    },
    {
      "id": "3b5859b6-0c46-4a76-8987-7fffe283ddb2",
      "title": "Massive Protests in Pakistan-Occupied Kashmir Demand Rights",
      "category": "NEWS",
      "time_to_read": "4m read",
      "cached_at": "2025-09-30T17:09:11.361Z"
    },
    {
      "id": "1116f8f0-a274-4c24-997b-9d843158beca",
      "title": "Ladakh's Demand for Sixth Schedule Autonomy Explained",
      "category": "NEWS",
      "time_to_read": "6m read",
      "cached_at": "2025-09-30T17:09:11.361Z"
    },
    {
      "id": "2c3644fe-52a1-42b8-b30c-e6334e495355",
      "title": "Massive Protests in PoK Over Political and Economic Grievances",
      "category": "NEWS",
      "time_to_read": "4m read",
      "cached_at": "2025-09-30T17:09:11.361Z"
    },
    {
      "id": "e4a7b8e9-d793-4eb4-9712-4558b86735fb",
      "title": "Trump's 20-Point Gaza Peace Plan: Details and Reactions",
      "category": "NEWS",
      "time_to_read": "4m read",
      "cached_at": "2025-09-30T17:09:11.361Z"
    },
    {
      "id": "158f76c7-b455-4b1b-ab53-c2941226985d",
      "title": "Surviving an Avalanche on Everest: A Near-Death Experience",
      "category": "PERSPECTIVES",
      "time_to_read": "65m read",
      "cached_at": "2025-09-30T17:09:11.361Z"
    }
  ],
  "total_time_to_read": "1h 39m read",
  "topics": [
    "NEWS",
    "PERSPECTIVES"
  ],
  "cached_at": "2025-09-30T17:09:11.361Z"
}