{
  "date": "2025-11-24",
  "articles": [
    {
      "id": "61334420-b831-4508-ae4c-765677c87d9a",
      "title": "Sadhguru on Enlightenment, Devotion, and Spiritual Practice",
      "category": "SPIRITUALITY",
      "time_to_read": "9m read",
      "cached_at": "2025-11-24T16:17:28.293Z"
    },
    {
      "id": "1820f7a3-7ea0-42e9-99b5-d40b94a6414c",
      "title": "Devotion Matters More Than Perfect Posture in Meditation",
      "category": "SPIRITUALITY",
      "time_to_read": "5m read",
      "cached_at": "2025-11-24T16:17:28.293Z"
    },
    {
      "id": "4b882b7f-3ff8-4775-943a-d77a60c45a73",
      "title": "French Navy Exposes Pakistan's Fake News Campaign",
      "category": "NEWS",
      "time_to_read": "4m read",
      "cached_at": "2025-11-24T16:17:28.293Z"
    },
    {
      "id": "699dd098-a349-4c69-9ac7-6049038157f6",
      "title": "Building Global Indian Consumer Brands: Ex-Myntra CEO's Strategy",
      "category": "BUSINESS",
      "time_to_read": "8m read",
      "cached_at": "2025-11-24T16:17:28.293Z"
    },
    {
      "id": "439c1541-f922-4ed8-9c1a-8d5fa2bcacce",
      "title": "Notebook LM Review: AI Learning Tool Strengths and Limitations",
      "category": "TECHNOLOGY",
      "time_to_read": "8m read",
      "cached_at": "2025-11-24T16:17:28.293Z"
    },
    {
      "id": "fc6a80ad-d65b-490f-9841-52beaee5357f",
      "title": "Major International Arms Smuggling Racket Busted in Delhi",
      "category": "NEWS",
      "time_to_read": "3m read",
      "cached_at": "2025-11-24T16:17:28.293Z"
    },
    {
      "id": "dc3c39b4-fdea-46d5-b665-3c2105e0d7b1",
      "title": "US Draft Peace Plan for Ukraine War and Geopolitical Shifts",
      "category": "NEWS",
      "time_to_read": "5m read",
      "cached_at": "2025-11-24T16:17:28.293Z"
    },
    {
      "id": "523f17f6-e79f-45da-bf41-a4247e88def3",
      "title": "Dope Tech Revisited: MX Master 4, Devialet Phantom, Tab S11 Ultra, Nikon ZR",
      "category": "TECHNOLOGY",
      "time_to_read": "7m read",
      "cached_at": "2025-11-24T16:17:28.293Z"
    },
    {
      "id": "abcade05-2cd7-4067-a25f-c07a86425021",
      "title": "Trump's 28-Point Plan to End the Ukraine War",
      "category": "NEWS",
      "time_to_read": "4m read",
      "cached_at": "2025-11-24T16:17:28.293Z"
    },
    {
      "id": "9425e5d9-cd0b-49bd-a87a-6cb3c381cf94",
      "title": "India Forms New Trilateral Partnership at G20 Summit",
      "category": "NEWS",
      "time_to_read": "5m read",
      "cached_at": "2025-11-24T16:17:28.293Z"
    },
    {
      "id": "24f650c0-7bdb-4d2f-a526-23abaf57b9eb",
      "title": "Rajnath Singh's Statement on Sindh's Potential Return to India",
      "category": "NEWS",
      "time_to_read": "5m read",
      "cached_at": "2025-11-24T16:17:28.293Z"
    },
    {
      "id": "2d7328af-3264-4b54-8965-7e4cf811177a",
      "title": "Swami Vivekananda on Eternal Progression as Bondage",
      "category": "SPIRITUALITY",
      "time_to_read": "5m read",
      "cached_at": "2025-11-24T16:17:28.293Z"
    },
    {
      "id": "9a0d5e57-b365-43c7-8bae-43d6ba0458a7",
      "title": "Acharya Prashant on Overcoming Self-Created Suffering",
      "category": "SPIRITUALITY",
      "time_to_read": "6m read",
      "cached_at": "2025-11-24T16:17:28.293Z"
    },
    {
      "id": "e1224cb7-de39-4480-9157-8f7742d38fe6",
      "title": "Afghanistan Offers India Major Tax Breaks to Boost Investment",
      "category": "BUSINESS",
      "time_to_read": "4m read",
      "cached_at": "2025-11-24T16:17:28.293Z"
    },
    {
      "id": "2bb2e5a0-fe91-49a6-b4f6-af7cf26b245a",
      "title": "US-Venezuela Crisis: Oil, Geopolitics, and Potential Conflict",
      "category": "NEWS",
      "time_to_read": "5m read",
      "cached_at": "2025-11-24T16:17:28.293Z"
    },
    {
      "id": "e8e78922-5519-4535-b39d-9fc699efc9df",
      "title": "Tejas Crash Analysis & India's Fighter Jet Crisis",
      "category": "NEWS",
      "time_to_read": "6m read",
      "cached_at": "2025-11-24T16:17:28.293Z"
    },
    {
      "id": "7ca71957-84a6-449e-b5b1-1f55aa017387",
      "title": "India's Plan to Boost Manufacturing to 25% of GDP",
      "category": "BUSINESS",
      "time_to_read": "5m read",
      "cached_at": "2025-11-24T16:17:28.293Z"
    },
    {
      "id": "81f7b7fe-49b6-4873-915b-57bec80b6c54",
      "title": "Delhi Blast: Doctor-Led Terror Network and Weapons Smuggling",
      "category": "NEWS",
      "time_to_read": "5m read",
      "cached_at": "2025-11-24T16:17:28.293Z"
    },
    {
      "id": "cf0a7368-3c20-4fb0-8c0f-a8102cf5b4fe",
      "title": "TCS Fined $194 Million in US Trade Secret Case",
      "category": "BUSINESS",
      "time_to_read": "4m read",
      "cached_at": "2025-11-24T16:17:28.293Z"
    },
    {
      "id": "dff44cee-dcd9-4521-b935-6f2644a6447b",
      "title": "Delhi Air Pollution Protest Marred by Maoist Slogans and Violence",
      "category": "NEWS",
      "time_to_read": "4m read",
      "cached_at": "2025-11-24T16:17:28.293Z"
    },
    {
      "id": "fdb6df86-480c-43b4-b6c0-748549bd36f1",
      "title": "Sri Ramakrishna on Spiritual Beliefs and Practices",
      "category": "SPIRITUALITY",
      "time_to_read": "7m read",
      "cached_at": "2025-11-24T16:17:28.293Z"
    },
    {
      "id": "7ca32812-45c8-4bcd-bb66-c08e9590c324",
      "title": "G20 Summit Adopts Declaration Despite US Boycott",
      "category": "NEWS",
      "time_to_read": "4m read",
      "cached_at": "2025-11-24T16:17:28.293Z"
    },
    {
      "id": "fc21ecfb-0f70-4085-81df-5c49b9f948e8",
      "title": "India-China Trade Deficit Rises Despite Border Tensions",
      "category": "BUSINESS",
      "time_to_read": "5m read",
      "cached_at": "2025-11-24T16:17:28.293Z"
    },
    {
      "id": "b76a6078-6317-486e-a451-68dbf6dfe210",
      "title": "French Navy Debunks Pakistani Media's Rafale Loss Claim",
      "category": "NEWS",
      "time_to_read": "3m read",
      "cached_at": "2025-11-24T16:17:28.293Z"
    },
    {
      "id": "d2039f81-4515-40ef-8e57-32a4953c0e39",
      "title": "Sudan's Civil War and Humanitarian Crisis Explained",
      "category": "NEWS",
      "time_to_read": "7m read",
      "cached_at": "2025-11-24T16:17:28.293Z"
    },
    {
      "id": "1d90c8c4-1d0a-417b-a407-a46e1e149a28",
      "title": "Karma and Rebirth in Hinduism: A Philosophical Overview",
      "category": "SPIRITUALITY",
      "time_to_read": "8m read",
      "cached_at": "2025-11-24T16:17:28.293Z"
    }
  ],
  "total_time_to_read": "2h 21m read",
  "topics": [
    "SPIRITUALITY",
    "NEWS",
    "BUSINESS",
    "TECHNOLOGY"
  ],
  "cached_at": "2025-11-24T16:17:28.293Z"
}