{
  "date": "2025-12-12",
  "articles": [
    {
      "id": "65158f1b-d077-4864-ac90-7d1de16ff84a",
      "title": "Australia Bans Social Media for Under-16s, Sparking Global Debate",
      "category": "NEWS",
      "time_to_read": "13m read",
      "cached_at": "2025-12-12T17:41:33.601Z"
    },
    {
      "id": "7674626a-97a0-418b-a61e-0c073ad7046c",
      "title": "Amazon Commits $35 Billion Investment in India by 2030",
      "category": "BUSINESS",
      "time_to_read": "5m read",
      "cached_at": "2025-12-12T17:41:33.601Z"
    },
    {
      "id": "8d369b8f-260e-4dbd-bd32-30be721b9ba1",
      "title": "Indore POCSO Court Sentences Man to Four Life Terms",
      "category": "NEWS",
      "time_to_read": "6m read",
      "cached_at": "2025-12-12T17:41:33.601Z"
    },
    {
      "id": "8fc960b2-9044-4d77-a4c8-49bb46f76b0f",
      "title": "India Offers 'Best-Ever' Trade Deal to US, Talks Ongoing",
      "category": "BUSINESS",
      "time_to_read": "5m read",
      "cached_at": "2025-12-12T17:41:33.601Z"
    },
    {
      "id": "ad3e8544-aa94-4b53-8928-fbe0b49d81f8",
      "title": "Mexico's 50% Tariff on India: Causes and Impacts",
      "category": "BUSINESS",
      "time_to_read": "6m read",
      "cached_at": "2025-12-12T17:41:33.602Z"
    },
    {
      "id": "ba5dd34c-ed57-465e-867a-6d2853beaeea",
      "title": "Amazon's $35 Billion Investment in India: AI, Exports, and Jobs",
      "category": "BUSINESS",
      "time_to_read": "6m read",
      "cached_at": "2025-12-12T17:41:33.602Z"
    },
    {
      "id": "8782056e-bd69-45c3-b521-9dbc575af974",
      "title": "Why Big Tech is Investing Billions in India",
      "category": "TECHNOLOGY",
      "time_to_read": "8m read",
      "cached_at": "2025-12-12T17:41:33.602Z"
    },
    {
      "id": "4b8bbc17-0c1d-4f19-bb23-ece6ce91f458",
      "title": "China's Territorial Claims on Russian Land and Regional Ambitions",
      "category": "NEWS",
      "time_to_read": "8m read",
      "cached_at": "2025-12-12T17:41:33.602Z"
    },
    {
      "id": "38bc087a-4ffd-4c78-b6e0-a9c0e6fae3fa",
      "title": "The C5 Concept: A Proposed New Global Power Group",
      "category": "NEWS",
      "time_to_read": "5m read",
      "cached_at": "2025-12-12T17:41:33.602Z"
    },
    {
      "id": "20570f02-fcc6-445c-84a7-982a9c1f7f9d",
      "title": "Report Suggests China Could Defeat US in Taiwan Conflict",
      "category": "NEWS",
      "time_to_read": "5m read",
      "cached_at": "2025-12-12T17:41:33.602Z"
    },
    {
      "id": "a8d77d2b-536a-42da-bcf8-b323dec1d03d",
      "title": "AI's Military Evolution and Global Security Concerns",
      "category": "TECHNOLOGY",
      "time_to_read": "6m read",
      "cached_at": "2025-12-12T17:41:33.602Z"
    },
    {
      "id": "c5e9f8bf-e60e-48eb-8436-f37c971537f2",
      "title": "India's Need for an Indigenous Air Defence System for Delhi",
      "category": "TECHNOLOGY",
      "time_to_read": "6m read",
      "cached_at": "2025-12-12T17:41:33.602Z"
    },
    {
      "id": "b82e474b-20ee-4030-b57b-1fbbab1fa837",
      "title": "Sadhguru Explains the True Nature and Power of Kundalini",
      "category": "SPIRITUALITY",
      "time_to_read": "6m read",
      "cached_at": "2025-12-12T17:41:33.602Z"
    },
    {
      "id": "a64afa32-243b-4349-a3e2-4c1f579fb9e6",
      "title": "India-US Trade Deal Faces Stalemate Over Market Access",
      "category": "BUSINESS",
      "time_to_read": "5m read",
      "cached_at": "2025-12-12T17:41:33.602Z"
    },
    {
      "id": "fd0ffced-a6f1-43ee-a82b-026c3423a1bf",
      "title": "US-India Trade Deal Stalls as Trump's Tariffs Face Legal Scrutiny",
      "category": "BUSINESS",
      "time_to_read": "5m read",
      "cached_at": "2025-12-12T17:41:33.602Z"
    },
    {
      "id": "0a0f2ab4-5511-4f83-b5c9-dd3def588010",
      "title": "US Approves $686 Million Support for Pakistan's F-16 Fleet",
      "category": "NEWS",
      "time_to_read": "5m read",
      "cached_at": "2025-12-12T17:41:33.602Z"
    }
  ],
  "total_time_to_read": "1h 40m read",
  "topics": [
    "NEWS",
    "BUSINESS",
    "TECHNOLOGY",
    "SPIRITUALITY"
  ],
  "cached_at": "2025-12-12T17:41:33.602Z"
}